toredis/__init__.py
toredis/_compat.py
toredis/client.py
toredis/commands.py
toredis/pipeline.py
toredis_latest-0.1.2.dist-info/licenses/AUTHORS
toredis_latest-0.1.2.dist-info/METADATA
toredis_latest-0.1.2.dist-info/WHEEL
toredis_latest-0.1.2.dist-info/top_level.txt
toredis_latest-0.1.2.dist-info/RECORD
