Metadata-Version: 2.4
Name: toredis-latest
Version: 0.1.2
Summary: Really simple async Redis client for Tornado
Home-page: http://github.com/mrjoes/toredis/
Author: Josh Marshall
Author-email: catchjosh@gmail.com
License: http://www.apache.org/licenses/LICENSE-2.0
License-File: AUTHORS
Requires-Dist: tornado
Requires-Dist: hiredis
Dynamic: author
Dynamic: author-email
Dynamic: home-page
Dynamic: license
Dynamic: license-file
Dynamic: requires-dist
Dynamic: summary
